Metadata-Version: 2.1
Name: ai-service-test-23-10-24
Version: 0.0.1
Summary: PYPI tutorial
Home-page: https://hello2_world.git/hello_world2
Author: wj
Author-email: hello_world2@helloworld.com
Classifier: Programming Language :: Python :: 3.8
Classifier: License :: OSI Approved :: GNU General Public License v3 (GPLv3)
Classifier: Operating System :: POSIX :: Linux
Requires-Python: >=3.8
Requires-Dist: absl-py (==1.4.0)
Requires-Dist: cachetools (==5.3.1)
Requires-Dist: certifi (==2023.5.7)
Requires-Dist: cffi (==1.16.0)
Requires-Dist: charset-normalizer (==3.1.0)
Requires-Dist: cmake (==3.26.4)
Requires-Dist: contourpy (==1.1.0)
Requires-Dist: google-auth (==2.21.0)
Requires-Dist: google-auth-oauthlib (==1.0.0)
Requires-Dist: GPUtil (==1.4.0)
Requires-Dist: grpcio (==1.58.0)
Requires-Dist: grpcio-tools (==1.58.0)
Requires-Dist: idna (==3.4)
Requires-Dist: imageio (==2.31.1)
Requires-Dist: imgaug (==0.4.0)
Requires-Dist: importlib-metadata (==6.7.0)
Requires-Dist: importlib-resources (==5.12.0)
Requires-Dist: jaraco.classes (==3.3.0)
Requires-Dist: jeepney (==0.8.0)
Requires-Dist: Jinja2 (==3.1.2)
Requires-Dist: joblib (==1.3.1)
Requires-Dist: keyring (==24.2.0)
Requires-Dist: MarkupSafe (==2.1.3)
Requires-Dist: matplotlib (==3.7.1)
Requires-Dist: mdurl (==0.1.2)
Requires-Dist: more-itertools (==10.1.0)
Requires-Dist: mpmath (==1.3.0)
Requires-Dist: networkx (==3.1)
Requires-Dist: nh3 (==0.2.14)
Requires-Dist: numpy (==1.24.4)
Requires-Dist: nvidia-cublas-cu11 (==11.10.3.66)
Requires-Dist: nvidia-cuda-cupti-cu11 (==11.7.101)
Requires-Dist: nvidia-cuda-nvrtc-cu11 (==11.7.99)
Requires-Dist: nvidia-cuda-runtime-cu11 (==11.7.99)
Requires-Dist: nvidia-cudnn-cu11 (==8.5.0.96)
Requires-Dist: nvidia-cufft-cu11 (==10.9.0.58)
Requires-Dist: nvidia-curand-cu11 (==10.2.10.91)
Requires-Dist: nvidia-cusolver-cu11 (==11.4.0.1)
Requires-Dist: nvidia-cusparse-cu11 (==11.7.4.91)
Requires-Dist: nvidia-ml-py3 (==7.352.0)
Requires-Dist: nvidia-nccl-cu11 (==2.14.3)
Requires-Dist: nvidia-nvtx-cu11 (==11.7.91)
Requires-Dist: oauthlib (==3.2.2)
Requires-Dist: opencv-python (==4.7.0.72)
Requires-Dist: pandas (==2.0.3)
Requires-Dist: Pillow (==9.5.0)
Requires-Dist: pkginfo (==1.9.6)
Requires-Dist: protobuf (==4.23.3)
Requires-Dist: pyasn1 (==0.5.0)
Requires-Dist: pyasn1-modules (==0.3.0)
Requires-Dist: pycparser (==2.21)
Requires-Dist: pyparsing (==3.1.0)
Requires-Dist: pytz (==2023.3)
Requires-Dist: PyWavelets (==1.4.1)
Requires-Dist: readme-renderer (==42.0)
Requires-Dist: requests (==2.31.0)
Requires-Dist: requests-oauthlib (==1.3.1)
Requires-Dist: requests-toolbelt (==1.0.0)
Requires-Dist: rfc3986 (==2.0.0)
Requires-Dist: rich (==13.6.0)
Requires-Dist: rsa (==4.9)
Requires-Dist: scikit-image (==0.21.0)
Requires-Dist: scikit-learn (==1.3.0)
Requires-Dist: scipy (==1.10.1)
Requires-Dist: SecretStorage (==3.3.3)
Requires-Dist: shapely (==2.0.1)
Requires-Dist: sympy (==1.12)
Requires-Dist: tensorboard (==2.13.0)
Requires-Dist: tensorboard-data-server (==0.7.1)
Requires-Dist: threadpoolctl (==3.2.0)
Requires-Dist: tifffile (==2023.4.12)
Requires-Dist: tqdm (==4.66.1)
Requires-Dist: triton (==2.0.0)
Requires-Dist: twine (==4.0.2)
Requires-Dist: typing-extensions (==4.7.0)
Requires-Dist: tzdata (==2023.3)
Requires-Dist: urllib3 (==1.26.16)
Requires-Dist: Werkzeug (==2.3.6)
Requires-Dist: zipp (==3.15.0)
